gnn-trainer/__init__.py
gnn-trainer/callbacks.py
gnn-trainer/dataloader.py
gnn-trainer/optimization.py
gnn-trainer/trainer.py
gnn-trainer/trainer_utils.py
gnn-trainer/training_args.py
gnn_trainer/__init__.py
gnn_trainer/callbacks.py
gnn_trainer/dataloader.py
gnn_trainer/optimization.py
gnn_trainer/trainer.py
gnn_trainer/trainer_utils.py
gnn_trainer/training_args.py
gnn_trainer-0.0.11.dist-info/LICENSE
gnn_trainer-0.0.11.dist-info/METADATA
gnn_trainer-0.0.11.dist-info/WHEEL
gnn_trainer-0.0.11.dist-info/top_level.txt
gnn_trainer-0.0.11.dist-info/RECORD
