Metadata-Version: 2.1
Name: gnn-trainer
Version: 0.0.11
Summary: A HuggingFace style trainer for graph neural network models
Home-page: UNKNOWN
Author: Joshua Melton
Author-email: jmelto30@uncc.edu
License: MIT
Keywords: pytorch,graph machine learning,graph representation learning,graph neural networks
Platform: UNKNOWN
License-File: LICENSE
Requires-Dist: numpy (>=1.16.0)
Requires-Dist: requests
Requires-Dist: scikit-learn (>=0.20.0)
Requires-Dist: tqdm
Requires-Dist: torch (>=1.6.0)
